adr/__init__.py
adr/__main__.py
adr/adr_manager.py
adr/cli.py
adr/config.py
adr/services.py
adr/template_engine.py
adr/domain/__init__.py
adr/domain/models.py
adr/domain/repository.py
adr/templates/madr.md
adr/templates/nygard.md
dark_madr-0.1.2.dist-info/METADATA
dark_madr-0.1.2.dist-info/WHEEL
dark_madr-0.1.2.dist-info/entry_points.txt
dark_madr-0.1.2.dist-info/RECORD
